rtl/pe.sv
module pe #(
    parameter DATA_WIDTH = 8
)
(
    input logic clk,
    input logic rst_n,
    input logic signed [DATA_WIDTH-1:0] act_in,
    input logic signed [DATA_WIDTH-1:0] weight,
    input logic signed [4*DATA_WIDTH-1:0] psum_in,
    input logic load_w,
    output logic signed [DATA_WIDTH-1:0] act_out,
    output logic signed [4*DATA_WIDTH-1:0] psum_out
);

reg signed [DATA_WIDTH-1:0] weight_reg;

always @(posedge clk) begin
    if (!rst_n) begin
        act_out <= 0;
        psum_out <= 0;
        weight_reg <= 0;
    end else begin
        if (load_w) 
            weight_reg <= weight; // Load weight into register
        // Perform MAC operation
        act_out <= act_in; // Pass activation to next PE
        psum_out <= psum_in + (act_in*weight_reg); // Update partial sum
    end
end

initial begin
    $dumpfile("pe.vcd");
    $dumpvars(0, pe);
end

endmodule

rtl/systolic_array/systolic_array.sv
module systolic_array (
    input logic clk,
    input logic rst_n,
    input logic signed [7:0] act_in [3:0],
    input logic [127:0] weight_bus,
    input logic load_w,
    output logic signed [31:0] psum_out [3:0]
);

logic signed [7:0] act_wire [3:0][4:0];
logic signed [31:0] psum_wire [4:0][3:0];

generate for (genvar i = 0; i < 4; i++) begin
    assign act_wire[i][0] = act_in[i];
end endgenerate

generate for (genvar i = 0; i < 4; i++) begin
    assign psum_wire[0][i] = 32'sd0;
end endgenerate

generate for (genvar i = 0; i < 4; i++) begin
    for (genvar j = 0; j < 4; j++) begin
         pe pe_inst(
            .clk(clk),
            .rst_n(rst_n),
            .act_in(act_wire[i][j]),
            .weight(weight_bus[(i*32 + j*8) +: 8]),
            .load_w(load_w),
            .psum_in(psum_wire[i][j]),
            .act_out(act_wire[i][j+1]),
            .psum_out(psum_wire[i+1][j])
        );
    end
end endgenerate

generate for (genvar j = 0; j < 4; j++) begin
    assign psum_out[j] = psum_wire[4][j];
end endgenerate


initial begin
    $dumpfile("systolic_array.vcd");
    $dumpvars(0, systolic_array);
end


endmodule

rtl/systolic_array/sim/systolic_array.vcd
$date
	Wed Aug 19 22:58:19 2026
$end
$version
	Icarus Verilog
$end
$timescale
	1ps
$end
$scope module systolic_array $end
$var wire 1 ! clk $end
$var wire 1 " load_w $end
$var wire 1 # rst_n $end
$var wire 128 $ weight_bus [127:0] $end
$scope begin genblk1[0] $end
$upscope $end
$scope begin genblk1[1] $end
$upscope $end
$scope begin genblk1[2] $end
$upscope $end
$scope begin genblk1[3] $end
$upscope $end
$scope begin genblk2[0] $end
$upscope $end
$scope begin genblk2[1] $end
$upscope $end
$scope begin genblk2[2] $end
$upscope $end
$scope begin genblk2[3] $end
$upscope $end
$scope begin genblk3[0] $end
$scope begin genblk4[0] $end
$scope module pe_inst $end
$var wire 8 % act_in [7:0] $end
$var wire 1 ! clk $end
$var wire 1 " load_w $end
$var wire 32 & psum_in [31:0] $end
$var wire 1 # rst_n $end
$var wire 8 ' weight [7:0] $end
$var reg 8 ( act_out [7:0] $end
$var reg 32 ) psum_out [31:0] $end
$var reg 8 * weight_reg [7:0] $end
$upscope $end
$upscope $end
$scope begin genblk4[1] $end
$scope module pe_inst $end
$var wire 8 + act_in [7:0] $end
$var wire 1 ! clk $end
$var wire 1 " load_w $end
$var wire 32 , psum_in [31:0] $end
$var wire 1 # rst_n $end
$var wire 8 - weight [7:0] $end
$var reg 8 . act_out [7:0] $end
$var reg 32 / psum_out [31:0] $end
$var reg 8 0 weight_reg [7:0] $end
$upscope $end
$upscope $end
$scope begin genblk4[2] $end
$scope module pe_inst $end
$var wire 8 1 act_in [7:0] $end
$var wire 1 ! clk $end
$var wire 1 " load_w $end
$var wire 32 2 psum_in [31:0] $end
$var wire 1 # rst_n $end
$var wire 8 3 weight [7:0] $end
$var reg 8 4 act_out [7:0] $end
$var reg 32 5 psum_out [31:0] $end
$var reg 8 6 weight_reg [7:0] $end
$upscope $end
$upscope $end
$scope begin genblk4[3] $end
$scope module pe_inst $end
$var wire 8 7 act_in [7:0] $end
$var wire 1 ! clk $end
$var wire 1 " load_w $end
$var wire 32 8 psum_in [31:0] $end
$var wire 1 # rst_n $end
$var wire 8 9 weight [7:0] $end
$var reg 8 : act_out [7:0] $end
$var reg 32 ; psum_out [31:0] $end
$var reg 8 < weight_reg [7:0] $end
$upscope $end
$upscope $end
$upscope $end
$scope begin genblk3[1] $end
$scope begin genblk4[0] $end
$scope module pe_inst $end
$var wire 8 = act_in [7:0] $end
$var wire 1 ! clk $end
$var wire 1 " load_w $end
$var wire 32 > psum_in [31:0] $end
$var wire 1 # rst_n $end
$var wire 8 ? weight [7:0] $end
$var reg 8 @ act_out [7:0] $end
$var reg 32 A psum_out [31:0] $end
$var reg 8 B weight_reg [7:0] $end
$upscope $end
$upscope $end
$scope begin genblk4[1] $end
$scope module pe_inst $end
$var wire 8 C act_in [7:0] $end
$var wire 1 ! clk $end
$var wire 1 " load_w $end
$var wire 32 D psum_in [31:0] $end
$var wire 1 # rst_n $end
$var wire 8 E weight [7:0] $end
$var reg 8 F act_out [7:0] $end
$var reg 32 G psum_out [31:0] $end
$var reg 8 H weight_reg [7:0] $end
$upscope $end
$upscope $end
$scope begin genblk4[2] $end
$scope module pe_inst $end
$var wire 8 I act_in [7:0] $end
$var wire 1 ! clk $end
$var wire 1 " load_w $end
$var wire 32 J psum_in [31:0] $end
$var wire 1 # rst_n $end
$var wire 8 K weight [7:0] $end
$var reg 8 L act_out [7:0] $end
$var reg 32 M psum_out [31:0] $end
$var reg 8 N weight_reg [7:0] $end
$upscope $end
$upscope $end
$scope begin genblk4[3] $end
$scope module pe_inst $end
$var wire 8 O act_in [7:0] $end
$var wire 1 ! clk $end
$var wire 1 " load_w $end
$var wire 32 P psum_in [31:0] $end
$var wire 1 # rst_n $end
$var wire 8 Q weight [7:0] $end
$var reg 8 R act_out [7:0] $end
$var reg 32 S psum_out [31:0] $end
$var reg 8 T weight_reg [7:0] $end
$upscope $end
$upscope $end
$upscope $end
$scope begin genblk3[2] $end
$scope begin genblk4[0] $end
$scope module pe_inst $end
$var wire 8 U act_in [7:0] $end
$var wire 1 ! clk $end
$var wire 1 " load_w $end
$var wire 32 V psum_in [31:0] $end
$var wire 1 # rst_n $end
$var wire 8 W weight [7:0] $end
$var reg 8 X act_out [7:0] $end
$var reg 32 Y psum_out [31:0] $end
$var reg 8 Z weight_reg [7:0] $end
$upscope $end
$upscope $end
$scope begin genblk4[1] $end
$scope module pe_inst $end
$var wire 8 [ act_in [7:0] $end
$var wire 1 ! clk $end
$var wire 1 " load_w $end
$var wire 32 \ psum_in [31:0] $end
$var wire 1 # rst_n $end
$var wire 8 ] weight [7:0] $end
$var reg 8 ^ act_out [7:0] $end
$var reg 32 _ psum_out [31:0] $end
$var reg 8 ` weight_reg [7:0] $end
$upscope $end
$upscope $end
$scope begin genblk4[2] $end
$scope module pe_inst $end
$var wire 8 a act_in [7:0] $end
$var wire 1 ! clk $end
$var wire 1 " load_w $end
$var wire 32 b psum_in [31:0] $end
$var wire 1 # rst_n $end
$var wire 8 c weight [7:0] $end
$var reg 8 d act_out [7:0] $end
$var reg 32 e psum_out [31:0] $end
$var reg 8 f weight_reg [7:0] $end
$upscope $end
$upscope $end
$scope begin genblk4[3] $end
$scope module pe_inst $end
$var wire 8 g act_in [7:0] $end
$var wire 1 ! clk $end
$var wire 1 " load_w $end
$var wire 32 h psum_in [31:0] $end
$var wire 1 # rst_n $end
$var wire 8 i weight [7:0] $end
$var reg 8 j act_out [7:0] $end
$var reg 32 k psum_out [31:0] $end
$var reg 8 l weight_reg [7:0] $end
$upscope $end
$upscope $end
$upscope $end
$scope begin genblk3[3] $end
$scope begin genblk4[0] $end
$scope module pe_inst $end
$var wire 8 m act_in [7:0] $end
$var wire 1 ! clk $end
$var wire 1 " load_w $end
$var wire 32 n psum_in [31:0] $end
$var wire 1 # rst_n $end
$var wire 8 o weight [7:0] $end
$var reg 8 p act_out [7:0] $end
$var reg 32 q psum_out [31:0] $end
$var reg 8 r weight_reg [7:0] $end
$upscope $end
$upscope $end
$scope begin genblk4[1] $end
$scope module pe_inst $end
$var wire 8 s act_in [7:0] $end
$var wire 1 ! clk $end
$var wire 1 " load_w $end
$var wire 32 t psum_in [31:0] $end
$var wire 1 # rst_n $end
$var wire 8 u weight [7:0] $end
$var reg 8 v act_out [7:0] $end
$var reg 32 w psum_out [31:0] $end
$var reg 8 x weight_reg [7:0] $end
$upscope $end
$upscope $end
$scope begin genblk4[2] $end
$scope module pe_inst $end
$var wire 8 y act_in [7:0] $end
$var wire 1 ! clk $end
$var wire 1 " load_w $end
$var wire 32 z psum_in [31:0] $end
$var wire 1 # rst_n $end
$var wire 8 { weight [7:0] $end
$var reg 8 | act_out [7:0] $end
$var reg 32 } psum_out [31:0] $end
$var reg 8 ~ weight_reg [7:0] $end
$upscope $end
$upscope $end
$scope begin genblk4[3] $end
$scope module pe_inst $end
$var wire 8 !" act_in [7:0] $end
$var wire 1 ! clk $end
$var wire 1 " load_w $end
$var wire 32 "" psum_in [31:0] $end
$var wire 1 # rst_n $end
$var wire 8 #" weight [7:0] $end
$var reg 8 $" act_out [7:0] $end
$var reg 32 %" psum_out [31:0] $end
$var reg 8 &" weight_reg [7:0] $end
$upscope $end
$upscope $end
$upscope $end
$scope begin genblk5[0] $end
$upscope $end
$scope begin genblk5[1] $end
$upscope $end
$scope begin genblk5[2] $end
$upscope $end
$scope begin genblk5[3] $end
$upscope $end
$scope begin $ivl_for_loop0 $end
$var integer 32 '" i [31:0] $end
$upscope $end
$upscope $end
$scope module systolic_array $end
$var reg 8 (" \act_in[0] [7:0] $end
$upscope $end
$scope module systolic_array $end
$var reg 32 )" \psum_out[0] [31:0] $end
$upscope $end
$scope module systolic_array $end
$var reg 8 *" \act_in[1] [7:0] $end
$upscope $end
$scope module systolic_array $end
$var reg 32 +" \psum_out[1] [31:0] $end
$upscope $end
$scope module systolic_array $end
$var reg 8 ," \act_in[2] [7:0] $end
$upscope $end
$scope module systolic_array $end
$var reg 32 -" \psum_out[2] [31:0] $end
$upscope $end
$scope module systolic_array $end
$var reg 8 ." \act_in[3] [7:0] $end
$upscope $end
$scope module systolic_array $end
$var reg 32 /" \psum_out[3] [31:0] $end
$upscope $end
$enddefinitions $end
#0
$dumpvars
b0 /"
b0 ."
b0 -"
b0 ,"
b0 +"
b0 *"
b0 )"
b0 ("
b100 '"
b0 &"
b0 %"
b0 $"
bz #"
b0 ""
b0 !"
b0 ~
b0 }
b0 |
bz {
b0 z
b0 y
b0 x
b0 w
b0 v
bz u
b0 t
b0 s
b0 r
b0 q
b0 p
bz o
b0 n
b0 m
b0 l
b0 k
b0 j
bz i
b0 h
b0 g
b0 f
b0 e
b0 d
bz c
b0 b
b0 a
b0 `
b0 _
b0 ^
bz ]
b0 \
b0 [
b0 Z
b0 Y
b0 X
bz W
b0 V
b0 U
b0 T
b0 S
b0 R
bz Q
b0 P
b0 O
b0 N
b0 M
b0 L
bz K
b0 J
b0 I
b0 H
b0 G
b0 F
bz E
b0 D
b0 C
b0 B
b0 A
b0 @
bz ?
b0 >
b0 =
b0 <
b0 ;
b0 :
bz 9
b0 8
b0 7
b0 6
b0 5
b0 4
bz 3
b0 2
b0 1
b0 0
b0 /
b0 .
bz -
b0 ,
b0 +
b0 *
b0 )
b0 (
bz '
b0 &
b0 %
bz $
0#
z"
1!
$end
#5000
0!
#10000
1#
1!
#15000
0!
#20000
b1 '
b10 -
b0 3
b11111111 9
b0 ?
b1 E
b1 K
b10 Q
b10 W
b0 ]
b1 c
b1 i
b1 o
b1 u
b0 {
b1 #"
1"
b1000000000000000100000001000000010000000100000000000000100000001000000001000000010000000011111111000000000000001000000001 $
1!
#25000
0!
#30000
b11 %
b11 ("
0"
b1 &"
b1 x
b1 r
b1 l
b1 f
b10 Z
b10 T
b1 N
b1 H
b11111111 <
b10 0
b1 *
1!
#35000
0!
#40000
b11111111 =
b11111111 *"
b11 )
b11 >
b11 (
b11 +
1!
#45000
0!
#50000
b11111110 U
b11111110 ,"
b11 A
b11 V
b11111111 @
b11111111 C
b110 /
b110 D
b11 .
b11 1
1!
#55000
0!
#60000
b100 m
b100 ."
b11 4
b11 7
b101 G
b101 \
b11111111 F
b11111111 I
b11111111111111111111111111111111 Y
b11111111111111111111111111111111 n
b11111110 X
b11111110 [
1!
#65000
0!
#70000
b11 )"
b11 q
b100 p
b100 s
b101 _
b101 t
b11111110 ^
b11111110 a
b11111111111111111111111111111111 M
b11111111111111111111111111111111 b
b11111111 L
b11111111 O
b11111111111111111111111111111101 ;
b11111111111111111111111111111101 P
b11 :
1!
#75000
0!
#80000
b11111111111111111111111111111011 S
b11111111111111111111111111111011 h
b11111111 R
b11111111111111111111111111111101 e
b11111111111111111111111111111101 z
b11111110 d
b11111110 g
b1001 +"
b1001 w
b100 v
b100 y
1!
#85000
0!
#90000
b11111111111111111111111111111101 -"
b11111111111111111111111111111101 }
b100 |
b100 !"
b11111111111111111111111111111001 k
b11111111111111111111111111111001 ""
b11111110 j
1!
#95000
0!
#100000
b11111111111111111111111111111101 /"
b11111111111111111111111111111101 %"
b100 $"
1!
